chapa/__init__.py
chapa/api.py
chapa/webhook.py
chapa_py9-0.1.5.dist-info/licenses/LICENSE
chapa_py9-0.1.5.dist-info/METADATA
chapa_py9-0.1.5.dist-info/WHEEL
chapa_py9-0.1.5.dist-info/top_level.txt
chapa_py9-0.1.5.dist-info/RECORD
