Metadata-Version: 2.4
Name: chapa-py9
Version: 0.1.5
Summary: Python SDK for Chapa API https://developer.chapa.co
Home-page: https://github.com/chapimenge3/chapa
Author: Temkin Mengistu (Chapi)
Author-email: chapimenge3@gmail.com
Project-URL: Source, https://github.com/chapimenge3/chapa
Project-URL: Bug Tracker, https://github.com/chapimenge3/chapa/issues
Classifier: Programming Language :: Python :: 3
Classifier: License :: OSI Approved :: MIT License
Classifier: Operating System :: OS Independent
Classifier: Development Status :: 3 - Alpha
Classifier: Intended Audience :: Developers
Classifier: Topic :: Software Development :: Libraries :: Python Modules
Requires-Python: >=3.6
License-File: LICENSE
Requires-Dist: httpx>=0.22.0
Dynamic: author
Dynamic: author-email
Dynamic: classifier
Dynamic: description
Dynamic: description-content-type
Dynamic: home-page
Dynamic: license-file
Dynamic: project-url
Dynamic: requires-dist
Dynamic: requires-python
Dynamic: summary
